newsman/__init__.py
newsman/factories.py
newsman/news.py
newsman/page.py
newsman/processor.py
newsman/reader.py
newsman/pipeline/__init__.py
newsman/pipeline/byte2html.py
newsman/pipeline/html2image.py
newsman/pipeline/html2meta.py
newsman/pipeline/html2text.py
newsman/pipeline/pipe.py
newsman/pipeline/pipeline.py
newsman/pipeline/text2title.py
newsman/scraping/__init__.py
newsman/scraping/filtering.py
newsman/scraping/scraper.py
newsman/utils/__init__.py
newsman/utils/decoding.py
newsman/utils/url.py
newsman-1.1.0.dist-info/LICENSE
newsman-1.1.0.dist-info/METADATA
newsman-1.1.0.dist-info/WHEEL
newsman-1.1.0.dist-info/top_level.txt
newsman-1.1.0.dist-info/RECORD
