Metadata-Version: 2.1
Name: newsman
Version: 1.1.0
Summary: A tool for web news scraping.
Home-page: https://github.com/acapitanelli/newsman
Author: Andrea Capitanelli
Author-email: andrea.capitanelli@gmail.com
Maintainer: Andrea Capitanelli
Maintainer-email: andrea.capitanelli@gmail.com
License: MIT
Keywords: press articles text extraction
Platform: UNKNOWN
Classifier: Development Status :: 3 - Alpha
Classifier: License :: OSI Approved :: MIT License
Classifier: Operating System :: POSIX :: Linux
Classifier: Programming Language :: Python :: 3
Classifier: Topic :: Office/Business :: News/Diary
Requires-Python: >=3.6.0
Requires-Dist: chardet
Requires-Dist: requests
